{
  "article701225819": {
    "propaganda_1": {
      "text":"South Florida Muslim Leader Sofian Zakkout’s David Duke Day",
      "span_1": {
        "span": "",
        "label": 0,
        "start_char": 0,
        "end_index": 0,
        "probability": 0
      }
    },
    "propaganda_2": {
      "text":"David Duke, the white supremacist icon and former Grand Wizard of the Ku Klux Klan, has been denounced by many as a hatemonger, and rightfully so.",
      "span_1": {
        "span": "hatemonger",
        "label": 10,
        "start_char": 116,
        "end_index": 126,
        "probability": 0.63
      },
      "span_2": {
        "span": "white supremacist icon",
        "label": 10,
        "start_char": 16,
        "end_index": 38,
        "probability": 0.48
      },
      "span_3": {
        "span": "Ku Klux Klan",
        "label": 2,
        "start_char": 70,
        "end_index": 82,
        "probability": 0.52
      }
    },
    "propaganda_3": {
      "text":"However, one individual who represents the Muslim community of South Florida, Sofian Zakkout, is enamored with Duke and has been promoting Duke’s bigoted work for many years.",
      "span_1": {
        "span": "enamored",
        "label": 9,
        "start_char": 97,
        "end_index": 105,
        "probability": 0.53
      }
    },
    "propaganda_4": {
      "text":"At this same rally, a white nationalist plowed his car into a group of people who were protesting the rally, killing one.",
      "span_1": {
        "span": "white nationalist plowed his car into a group of people who were protesting the rally, killing one",
        "label": 2,
        "start_char": 22,
        "end_index": 120,
        "probability": 0.35
      }
    },
    "propaganda_5": {
      "text":"David Duke Exposes the Real Racist Jewish Supremacists Who Orchestrate the Destruction of European Mankind…’ Above the posting, Zakkout wrote of Duke, “I respect him for his honesty!”",
      "span_1": {
        "span": "Racist Jewish Supremacists",
        "label": 10,
        "start_char": 28,
        "end_index": 54,
        "probability": 0.7
      },
      "span_2": {
        "span": "Destruction",
        "label": 9,
        "start_char": 75,
        "end_index": 86,
        "probability": 0.67
      }
    },
    "propaganda_6": {
      "text":"In October 2015, Zakkout posted to Facebook a Duke video, within which Duke makes the wild claim that there has been a “complete takeover of American foreign policy and… American politics by Jewish extremists.” Above the video on Facebook, Zakkout praised Duke, exclaiming “David Duke, a man to believe in!”",
      "span_1": {
        "span": "wild",
        "label": 9,
        "start_char": 86,
        "end_index": 90,
        "probability": 0.5
      },
      "span_2": {
        "span": "Jewish extremists",
        "label": 10,
        "start_char": 191,
        "end_index": 208,
        "probability": 0.5
      },
      "span_3": {
        "span": "a man to believe in!",
        "label": 12,
        "start_char": 286,
        "end_index": 306,
        "probability": 0.7
      }
    }

  }
}